{
  "main": {
    "id": "ce11fbc8343d96b6",
    "type": "split",
    "children": [
      {
        "id": "dcc34e0443b5595d",
        "type": "tabs",
        "children": [
          {
            "id": "ac0e71b98551ac5f",
            "type": "leaf",
            "state": {
              "type": "markdown",
              "state": {
                "file": "Welcome.md",
                "mode": "source",
                "source": false
              }
            }
          }
        ]
      },
      {
        "id": "fa821f5ff3bdc6e0",
        "type": "tabs",
        "children": [
          {
            "id": "5785ec56a0217e0c",
            "type": "leaf",
            "state": {
              "type": "graph",
              "state": {}
            }
          }
        ]
      }
    ],
    "direction": "vertical"
  },
  "left": {
    "id": "921640790ac60251",
    "type": "split",
    "children": [
      {
        "id": "dc6960be0e5910ec",
        "type": "tabs",
        "children": [
          {
            "id": "f89b5396d9a859b6",
            "type": "leaf",
            "state": {
              "type": "file-explorer",
              "state": {
                "sortOrder": "alphabetical"
              }
            }
          },
          {
            "id": "0771e49ea653cf83",
            "type": "leaf",
            "state": {
              "type": "search",
              "state": {
                "query": "",
                "matchingCase": false,
                "explainSearch": false,
                "collapseAll": false,
                "extraContext": false,
                "sortOrder": "alphabetical"
              }
            }
          },
          {
            "id": "ce8bbcd4541f8e94",
            "type": "leaf",
            "state": {
              "type": "bookmarks",
              "state": {}
            }
          }
        ]
      }
    ],
    "direction": "horizontal",
    "width": 300
  },
  "right": {
    "id": "99f429f8be16409b",
    "type": "split",
    "children": [
      {
        "id": "e681dd44b96ceeba",
        "type": "tabs",
        "children": [
          {
            "id": "b6fad8429d18eccc",
            "type": "leaf",
            "state": {
              "type": "backlink",
              "state": {
                "file": "Welcome.md",
                "collapseAll": false,
                "extraContext": false,
                "sortOrder": "alphabetical",
                "showSearch": false,
                "searchQuery": "",
                "backlinkCollapsed": false,
                "unlinkedCollapsed": true
              }
            }
          },
          {
            "id": "0106e0ad1cd69afd",
            "type": "leaf",
            "state": {
              "type": "outgoing-link",
              "state": {
                "file": "Welcome.md",
                "linksCollapsed": false,
                "unlinkedCollapsed": true
              }
            }
          },
          {
            "id": "e75032bab84b4b32",
            "type": "leaf",
            "state": {
              "type": "tag",
              "state": {
                "sortOrder": "frequency",
                "useHierarchy": true
              }
            }
          },
          {
            "id": "d168df6f809db1bd",
            "type": "leaf",
            "state": {
              "type": "outline",
              "state": {
                "file": "Welcome.md"
              }
            }
          }
        ]
      }
    ],
    "direction": "horizontal",
    "width": 300,
    "collapsed": true
  },
  "left-ribbon": {
    "hiddenItems": {
      "switcher:Open quick switcher": false,
      "graph:Open graph view": false,
      "canvas:Create new canvas": false,
      "daily-notes:Open today's daily note": false,
      "templates:Insert template": false,
      "command-palette:Open command palette": false
    }
  },
  "active": "ac0e71b98551ac5f",
  "lastOpenFiles": [
    "CHANGELOG/2024-05-09.md",
    "CHANGELOG/2024-05-08.md",
    "CHANGELOG/2024-04-19.md",
    "CHANGELOG/2024-04-10.md",
    "CHANGELOG",
    "writing prompts/2024-05-29.md",
    "writing prompts",
    "children of the damned/Notes on the Narrative.md",
    "children of the damned/01.md",
    "children of the damned/11.md",
    "children of the damned/05.md",
    "children of the damned/15.md",
    "children of the damned/04.md",
    "children of the damned/20.md",
    "children of the damned/14.md",
    "children of the damned/10.md",
    "children of the damned/07.md",
    "children of the damned/17.md",
    "children of the damned/03.md",
    "children of the damned/13.md",
    "children of the damned/02.md",
    "children of the damned/12.md",
    "children of the damned/06.md",
    "children of the damned/16.md",
    "children of the damned/09.md",
    "children of the damned/19.md",
    "children of the damned/08.md",
    "children of the damned/18.md",
    "children of the damned"
  ]
}